icp_agent/__init__.py
icp_agent/agent.py
icp_agent/client.py
icp_agent/system_state.py
icp_candid/__init__.py
icp_candid/_ic_candid_core.pyi
icp_candid/candid.py
icp_candid/did_loader.py
icp_canister/__init__.py
icp_canister/canister.py
icp_canister/cycles_wallet.py
icp_canister/governance.py
icp_canister/ledger.py
icp_canister/management.py
icp_certificate/__init__.py
icp_certificate/certificate.py
icp_core/__init__.py
icp_identity/__init__.py
icp_identity/identity.py
icp_principal/__init__.py
icp_principal/principal.py
icp_py_core-2.1.1.dist-info/licenses/LICENSE
icp_py_core-2.1.1.dist-info/METADATA
icp_py_core-2.1.1.dist-info/WHEEL
icp_py_core-2.1.1.dist-info/top_level.txt
icp_py_core-2.1.1.dist-info/RECORD
