Metadata-Version: 2.4
Name: icp-py-core
Version: 2.1.1
Summary: Core Python SDK for the Internet Computer: agent, candid, identity, principal, certificate.
Author: eliezhao
License: MIT License
Project-URL: Homepage, https://github.com/eliezhao/icp-py-core
Project-URL: Repository, https://github.com/eliezhao/icp-py-core
Project-URL: Issues, https://github.com/eliezhao/icp-py-core/issues
Requires-Python: >=3.8
License-File: LICENSE
Requires-Dist: httpx>=0.24
Requires-Dist: cbor2>=5.6.0
Requires-Dist: ecdsa>=0.18.0
Requires-Dist: PyNaCl>=1.5.0
Requires-Dist: ic_candid_parser>=0.1.0
Provides-Extra: bls
Requires-Dist: blst; extra == "bls"
Dynamic: license-file
